genderdeterminator/__init__.py
genderdeterminator/gender_determinator.py
genderdeterminator/words.csv
gender_determinator-0.1.dist-info/LICENSE
gender_determinator-0.1.dist-info/METADATA
gender_determinator-0.1.dist-info/WHEEL
gender_determinator-0.1.dist-info/top_level.txt
gender_determinator-0.1.dist-info/RECORD
