Metadata-Version: 2.1
Name: gender-determinator
Version: 0.1
Summary: Determines the gender of german nouns and provides some convenient methods
Home-page: https://github.com/Alpha200/gender-determinator
Author: Daniel Sendzik
Author-email: daniel@sendzik.eu
License: LGPL
Platform: UNKNOWN
